<?xml version="1.0" encoding="UTF-8"?>
<!DOCTYPE mapper PUBLIC "-//mybatis.org//DTD Mapper 3.0//EN" "http://mybatis.org/dtd/mybatis-3-mapper.dtd">
<mapper namespace="dao.ViesbutisMapper">
  <resultMap id="BaseResultMap" type="model.Viesbutis">
    <!--
      WARNING - @mbg.generated
      This element is automatically generated by MyBatis Generator, do not modify.
      This element was generated on Thu Mar 30 10:40:42 EEST 2017.
    -->
    <id column="Kodas" jdbcType="VARCHAR" property="kodas" />
    <result column="Pavadinimas" jdbcType="VARCHAR" property="pavadinimas" />
    <result column="Adresas" jdbcType="VARCHAR" property="adresas" />
  </resultMap>
  <delete id="deleteByPrimaryKey" parameterType="java.lang.String">
    <!--
      WARNING - @mbg.generated
      This element is automatically generated by MyBatis Generator, do not modify.
      This element was generated on Thu Mar 30 10:40:42 EEST 2017.
    -->
    delete from Viesbutis
    where Kodas = #{kodas,jdbcType=VARCHAR}
  </delete>
  <insert id="insert" keyColumn="Kodas" keyProperty="kodas" parameterType="model.Viesbutis" useGeneratedKeys="true">
    <!--
      WARNING - @mbg.generated
      This element is automatically generated by MyBatis Generator, do not modify.
      This element was generated on Thu Mar 30 10:40:42 EEST 2017.
    -->
    insert into Viesbutis (Pavadinimas, Adresas)
    values (#{pavadinimas,jdbcType=VARCHAR}, #{adresas,jdbcType=VARCHAR})
  </insert>
  <update id="updateByPrimaryKey" parameterType="model.Viesbutis">
    <!--
      WARNING - @mbg.generated
      This element is automatically generated by MyBatis Generator, do not modify.
      This element was generated on Thu Mar 30 10:40:42 EEST 2017.
    -->
    update Viesbutis
    set Pavadinimas = #{pavadinimas,jdbcType=VARCHAR},
      Adresas = #{adresas,jdbcType=VARCHAR}
    where Kodas = #{kodas,jdbcType=VARCHAR}
  </update>
  <select id="selectByPrimaryKey" parameterType="java.lang.String" resultMap="BaseResultMap">
    <!--
      WARNING - @mbg.generated
      This element is automatically generated by MyBatis Generator, do not modify.
      This element was generated on Thu Mar 30 10:40:42 EEST 2017.
    -->
    select Kodas, Pavadinimas, Adresas
    from Viesbutis
    where Kodas = #{kodas,jdbcType=VARCHAR}
  </select>
  <select id="selectAll" resultMap="BaseResultMap">
    <!--
      WARNING - @mbg.generated
      This element is automatically generated by MyBatis Generator, do not modify.
      This element was generated on Thu Mar 30 10:40:42 EEST 2017.
    -->
    select Kodas, Pavadinimas, Adresas
    from Viesbutis
  </select>
</mapper>